ranking_metrics_torch/__init__.py
ranking_metrics_torch/avg_precision.py
ranking_metrics_torch/common.py
ranking_metrics_torch/cumulative_gain.py
ranking_metrics_torch/precision_recall.py
ranking_metrics_torch-0.3.0.dist-info/LICENSE.md
ranking_metrics_torch-0.3.0.dist-info/WHEEL
ranking_metrics_torch-0.3.0.dist-info/METADATA
ranking_metrics_torch-0.3.0.dist-info/RECORD
