Metadata-Version: 2.1
Name: ranking-metrics-torch
Version: 0.3.0
Summary: Common ranking metrics implemented with PyTorch
Author: Karl Higley
Author-email: kmhigley@gmail.com
Requires-Python: >=3.7,<4.0
Classifier: Programming Language :: Python :: 3
Classifier: Programming Language :: Python :: 3.7
Classifier: Programming Language :: Python :: 3.8
Requires-Dist: torch (>=1.5.0,<2.0.0)
